Metadata-Version: 1.1
Name: syno
Version: 0.0.5
Summary: Synology API wrapper with aiohttp/asyncio
Home-page: http://github.com/bobuk/syno
Author: Grigory Bakunov
Author-email: thebobuk@ya.ru
License: UNKNOWN
Platform: UNKNOWN
Requires: aiohttp
Requires: asyncio
Requires: async_timeout
